airflow_dataform_parser/__init__.py
airflow_dataform_parser/dataform_declaration_object.py
airflow_dataform_parser/dataform_object.py
airflow_dataform_parser/dataform_object_list.py
airflow_dataform_parser/dataform_parser.py
airflow_dataform_parser/dataform_table_object.py
airflow_dataform_parser-0.1.0.dist-info/LICENSE
airflow_dataform_parser-0.1.0.dist-info/METADATA
airflow_dataform_parser-0.1.0.dist-info/WHEEL
airflow_dataform_parser-0.1.0.dist-info/top_level.txt
airflow_dataform_parser-0.1.0.dist-info/RECORD
