Metadata-Version: 2.1
Name: airflow_dataform_parser
Version: 0.1.0
Summary: Parser get dataform compile output and generates required task for airflow.
Home-page: https://github.com/EmreCelikkolOredata/airflow_dataform_parser
Author: Emre Celikkol
Author-email: emrecelikkol92@gmail.com
Project-URL: Documentation, https://github.com/EmreCelikkolOredata/airflow_dataform_parser
Project-URL: Bug Reports, https://github.com/EmreCelikkolOredata/airflow_dataform_parser
Project-URL: Source Code, https://github.com/EmreCelikkolOredata/airflow_dataform_parser
Keywords: dataform,airflow,gcp,bigquery,pypi,package
Classifier: Development Status :: 3 - Alpha
Classifier: Intended Audience :: Developers
Classifier: Programming Language :: Python :: 3.10
Classifier: License :: OSI Approved :: MIT License
Classifier: Operating System :: OS Independent
Requires-Python: >=3.9
License-File: LICENSE
